odoo8_addon_purchase_requisition_bid_selection-8.0.2.1.0.99.dev42-py3.8-nspkg.pth
odoo_addons/purchase_requisition_bid_selection/README.rst
odoo_addons/purchase_requisition_bid_selection/__init__.py
odoo_addons/purchase_requisition_bid_selection/__openerp__.py
odoo_addons/purchase_requisition_bid_selection/report.xml
odoo_addons/purchase_requisition_bid_selection/data/purchase.cancelreason.yml
odoo_addons/purchase_requisition_bid_selection/i18n/am.po
odoo_addons/purchase_requisition_bid_selection/i18n/ar.po
odoo_addons/purchase_requisition_bid_selection/i18n/bg.po
odoo_addons/purchase_requisition_bid_selection/i18n/bs.po
odoo_addons/purchase_requisition_bid_selection/i18n/ca.po
odoo_addons/purchase_requisition_bid_selection/i18n/ca_ES.po
odoo_addons/purchase_requisition_bid_selection/i18n/cs.po
odoo_addons/purchase_requisition_bid_selection/i18n/da.po
odoo_addons/purchase_requisition_bid_selection/i18n/de.po
odoo_addons/purchase_requisition_bid_selection/i18n/el_GR.po
odoo_addons/purchase_requisition_bid_selection/i18n/en_AU.po
odoo_addons/purchase_requisition_bid_selection/i18n/en_GB.po
odoo_addons/purchase_requisition_bid_selection/i18n/es.po
odoo_addons/purchase_requisition_bid_selection/i18n/es_AR.po
odoo_addons/purchase_requisition_bid_selection/i18n/es_BO.po
odoo_addons/purchase_requisition_bid_selection/i18n/es_CL.po
odoo_addons/purchase_requisition_bid_selection/i18n/es_CO.po
odoo_addons/purchase_requisition_bid_selection/i18n/es_CR.po
odoo_addons/purchase_requisition_bid_selection/i18n/es_DO.po
odoo_addons/purchase_requisition_bid_selection/i18n/es_EC.po
odoo_addons/purchase_requisition_bid_selection/i18n/es_ES.po
odoo_addons/purchase_requisition_bid_selection/i18n/es_MX.po
odoo_addons/purchase_requisition_bid_selection/i18n/es_PE.po
odoo_addons/purchase_requisition_bid_selection/i18n/es_PY.po
odoo_addons/purchase_requisition_bid_selection/i18n/es_VE.po
odoo_addons/purchase_requisition_bid_selection/i18n/et.po
odoo8_addon_purchase_requisition_bid_selection-8.0.2.1.0.99.dev42.dist-info/METADATA
odoo8_addon_purchase_requisition_bid_selection-8.0.2.1.0.99.dev42.dist-info/WHEEL
odoo8_addon_purchase_requisition_bid_selection-8.0.2.1.0.99.dev42.dist-info/namespace_packages.txt
odoo8_addon_purchase_requisition_bid_selection-8.0.2.1.0.99.dev42.dist-info/top_level.txt
odoo8_addon_purchase_requisition_bid_selection-8.0.2.1.0.99.dev42.dist-info/RECORD
